image_augmentor/__init__.py
image_augmentor/augmentor.py
image_augmentor/cli.py
sudhanshu_image_augmentor-0.2.dist-info/LICENSE
sudhanshu_image_augmentor-0.2.dist-info/METADATA
sudhanshu_image_augmentor-0.2.dist-info/WHEEL
sudhanshu_image_augmentor-0.2.dist-info/entry_points.txt
sudhanshu_image_augmentor-0.2.dist-info/top_level.txt
sudhanshu_image_augmentor-0.2.dist-info/RECORD
