Metadata-Version: 2.2
Name: sudhanshu_image_augmentor
Version: 0.2
Summary: A tool for augmenting images using various transformations.
Home-page: https://github.com/sudhanshuskarn/sudhanshu_image_augmentor
Author: Sudhanshu Shekhar Karn
Author-email: sudhanshuskarn@gmail.com
License: MIT
Classifier: Programming Language :: Python :: 3
Classifier: License :: OSI Approved :: MIT License
Classifier: Operating System :: OS Independent
Classifier: Intended Audience :: Developers
Classifier: Intended Audience :: Science/Research
Classifier: Topic :: Software Development :: Libraries :: Python Modules
Classifier: Topic :: Multimedia :: Graphics
Requires-Python: >=3.12
License-File: LICENSE
Requires-Dist: Pillow>=8.0.0
Requires-Dist: pytest>=6.0.0
Requires-Dist: psutil==6.1.1
Requires-Dist: pluggy>=1.0.0
Dynamic: author
Dynamic: author-email
Dynamic: classifier
Dynamic: description
Dynamic: description-content-type
Dynamic: home-page
Dynamic: license
Dynamic: requires-dist
Dynamic: requires-python
Dynamic: summary
